PyWeaver/Graph.py
PyWeaver/LibraryManager.py
PyWeaver/NodeTemplate.py
PyWeaver/Nodes.py
PyWeaver/Variable.py
PyWeaver/__init__.py
PyWeaver/client_pref.json
PyWeaver/code_parsing.py
PyWeaver/main.py
PyWeaver/model_manager.py
PyWeaver/refactor_magic.py
PyWeaver/results_encoder.py
PyWeaver/lib/core/Data Frame/Data Frame Apply Function/code.py
PyWeaver/lib/core/Data Frame/Data Frame Apply Function/meta.json
PyWeaver/lib/core/Data Frame/Data Frame Apply Function/ui.html
PyWeaver/lib/core/Data Frame/Data Frame Apply Function/ui_script.js
PyWeaver/lib/core/Excel/Excel Table/code.py
PyWeaver/lib/core/Excel/Excel Table/meta.json
PyWeaver/lib/core/Excel/Excel Table/ui.html
PyWeaver/lib/core/Excel/Excel Table/ui_script.js
PyWeaver/lib/core/Excel/Extract Series/code.py
PyWeaver/lib/core/Excel/Extract Series/meta.json
PyWeaver/lib/core/Excel/Extract Series/ui.html
PyWeaver/lib/core/Excel/Extract Series/ui_script.js
PyWeaver/lib/core/Excel/Numpy to Excel/code.py
PyWeaver/lib/core/Excel/Numpy to Excel/meta.json
PyWeaver/lib/core/Excel/Numpy to Excel/ui.html
PyWeaver/lib/core/Excel/Numpy to Excel/ui_script.js
PyWeaver/lib/core/Finance/Stock data/code.py
PyWeaver/lib/core/Finance/Stock data/meta.json
PyWeaver/lib/core/Finance/Stock data/ui.html
PyWeaver/lib/core/Finance/Stock data/ui_script.js
PyWeaver/lib/core/Functions/Piecewise Function/code.py
PyWeaver/lib/core/Functions/Piecewise Function/meta.json
PyWeaver/lib/core/Functions/Piecewise Function/ui.html
PyWeaver/lib/core/Functions/Piecewise Function/ui_script.js
PyWeaver/lib/core/Functions/Sigmoid/code.py
PyWeaver/lib/core/Functions/Sigmoid/meta.json
PyWeaver/lib/core/Functions/Sigmoid/ui.html
PyWeaver/lib/core/Functions/Sigmoid/ui_script.js
PyWeaver/lib/core/Input/Float/code.py
PyWeaver/lib/core/Input/Float/meta.json
PyWeaver/lib/core/Input/Float/ui.html
PyWeaver/lib/core/Input/Float/ui_script.js
PyWeaver/lib/core/Input/Integer/code.py
PyWeaver/lib/core/Input/Integer/meta.json
PyWeaver/lib/core/Input/Integer/ui.html
pyweaver-0.0.10.dist-info/LICENSE
pyweaver-0.0.10.dist-info/METADATA
pyweaver-0.0.10.dist-info/WHEEL
pyweaver-0.0.10.dist-info/top_level.txt
pyweaver-0.0.10.dist-info/RECORD
