Metadata-Version: 2.1
Name: pyweaver
Version: 0.0.10
Summary: Web based Python visual programming
Home-page: https://github.com/fleskovar/PyWeaver
Author: Example Author
Author-email: francisco.leskovar@gmail.com
License: UNKNOWN
Download-URL: https://github.com/fleskovar/PyWeaver/releases/download/v0.0.10/pyweaver-0.0.10.tar.gz
Platform: UNKNOWN
Classifier: Programming Language :: Python :: 3
Classifier: License :: OSI Approved :: MIT License
Classifier: Operating System :: Microsoft :: Windows
Requires-Dist: flask
Requires-Dist: flask-socketio
Requires-Dist: numpy
Requires-Dist: xmltodict
Requires-Dist: pandas
Requires-Dist: scipy
Requires-Dist: ruptures
